minion/__init__.py
minion/cli.py
minion/minion.py
graph_mem-0.1.0.dist-info/AUTHORS.rst
graph_mem-0.1.0.dist-info/LICENSE
graph_mem-0.1.0.dist-info/METADATA
graph_mem-0.1.0.dist-info/WHEEL
graph_mem-0.1.0.dist-info/top_level.txt
graph_mem-0.1.0.dist-info/RECORD
