Metadata-Version: 2.1
Name: graph-mem
Version: 0.1.0
Summary: Graph memory
Home-page: https://github.com/femto/minion
Author: Your Name
Author-email: femto Zheng <femtowin@gmail.com>
Maintainer-email: femto Zheng <femtowin@gmail.com>
License: MIT license
Project-URL: bugs, https://github.com/femto/minion/issues
Project-URL: changelog, https://github.com/femto/minion/blob/master/changelog.md
Project-URL: homepage, https://github.com/femto/minion
Requires-Python: >=3.6
License-File: LICENSE
License-File: AUTHORS.rst
Requires-Dist: typer
Provides-Extra: dev
Requires-Dist: coverage ; extra == 'dev'
Requires-Dist: mypy ; extra == 'dev'
Requires-Dist: pytest ; extra == 'dev'
Requires-Dist: ruff ; extra == 'dev'
